.coveragerc
.dockerignore
.gitignore
Dockerfile
Makefile
README.md
docker-compose.yml
make.bat
requirements.txt
setup.cfg
setup.py
test-requirements.txt
.circleci/config.yml
WTDpy.egg-info/PKG-INFO
WTDpy.egg-info/SOURCES.txt
WTDpy.egg-info/dependency_links.txt
WTDpy.egg-info/not-zip-safe
WTDpy.egg-info/requires.txt
WTDpy.egg-info/top_level.txt
docs/conf.py
docs/examples.rst
docs/index.rst
docs/installation.rst
docs/wtdpy.rst
tests/__init__.py
tests/test_historical_data.py
tests/test_search.py
tests/test_search_symbols.py
wtdpy/__init__.py
wtdpy/wtdpy.py