Metadata-Version: 2.1
Name: WTDpy
Version: 0.0.3
Summary: Basic calls to the World Trading Data API with Python.
Home-page: https://github.com/uijl/wtdpy
Author: Joris den Uijl
Author-email: jorisdenuijl@gmail.com
License: UNKNOWN
Keywords: wtdpy,world trading data,API
Platform: any
Classifier: Natural Language :: English
Classifier: Programming Language :: Python :: 3
Classifier: Operating System :: OS Independent
